{"name":"Diabetes-dashboard","tagline":"","body":"[![Build Status](http://img.shields.io/travis/pikesley/diabetes-dashboard.svg)](https://travis-ci.org/pikesley/diabetes-dashboard)\r\n[![Dependency Status](http://img.shields.io/gemnasium/pikesley/diabetes-dashboard.svg)](https://gemnasium.com/pikesley/diabetes-dashboard)\r\n[![Coverage Status](http://img.shields.io/coveralls/pikesley/diabetes-dashboard.svg)](https://coveralls.io/r/pikesley/diabetes-dashboard)\r\n[![Code Climate](http://img.shields.io/codeclimate/github/pikesley/diabetes-dashboard.svg)](https://codeclimate.com/github/pikesley/diabetes-dashboard)\r\n[![License](http://img.shields.io/:license-mit-blue.svg)](http://pikesley.mit-license.org)\r\n[![Badges](http://img.shields.io/:badges-6/6-ff6799.svg)](https://github.com/pikesley/badger)\r\n\r\nA Dashing dashboard, driven by my [Pancreas API](http://pancreas-api.herokuapp.com/). Right now it shows:\r\n\r\n* Daily, weekly and 30-day blood-glucose graphs and averages\r\n* Weekly breakfast, lunch, dinner and bedtime medication graphs and averages\r\n* Latest HbA1c\r\n\r\nThere'll be a lot more sophisticated stuff here once I've worked out Coffeescript and [Rickshaw](http://code.shutterstock.com/rickshaw/)\r\n\r\n# Deployment\r\n\r\nThis is a straight-up Rack app, it should deploy right onto Heroku. The Heroku environment will need to know about \r\n\r\n* `METRICS_API_USERNAME` and \r\n* `METRICS_API_PASSWORD` \r\n\r\nto access the Pancreas API (you'll have set these [here](http://pancreas-api.herokuapp.com/#dropbox-integration)), and \r\n\r\n* `DASHBOARD_USERNAME` and\r\n* `DASHBOARD_PASSWORD`\r\n\r\nwhich will allow you into the dashboard\r\n\r\n# Dashing is awesome\r\n\r\nSee [http://shopify.github.com/dashing](http://shopify.github.com/dashing) for more on Dashing\r\n","google":"","note":"Don't delete this file! It's used internally to help with page regeneration."}